abgpt/__init__.py
abgpt/generate.py
abgpt-0.1.2.dist-info/LICENSE
abgpt-0.1.2.dist-info/METADATA
abgpt-0.1.2.dist-info/WHEEL
abgpt-0.1.2.dist-info/entry_points.txt
abgpt-0.1.2.dist-info/top_level.txt
abgpt-0.1.2.dist-info/RECORD
