Metadata-Version: 2.1
Name: abgpt
Version: 0.1.2
Summary: AbGPT: De Novo B-Cell Receptor Design via Generative Language Modeling
Home-page: https://github.com/deskk/AbGPT
Author: Desmond Kuan, Amir Barati Farimani
Author-email: barati@cmu.edu
License: MIT
Classifier: Programming Language :: Python :: 3
Classifier: License :: OSI Approved :: MIT License
Classifier: Operating System :: OS Independent
Requires-Python: >=3.6
License-File: LICENSE
Requires-Dist: numpy>=1.21.2
Requires-Dist: tokenizers>=0.14.0
Requires-Dist: torch>=2.0.1
Requires-Dist: tqdm>=4.66.1
Requires-Dist: transformers==4.44.2
